{
  "map": "map2.csv",
  "entities": [
    {
      "name": "Player",
      "x": 180,
      "y": 170,
      "health": 7,
      "maxHealth": 10,
      "inventory": [
        {
          "name": "Gun",
          "bulletVelocity": 2,
          "fireRate": 10,
          "damage": 1
        },
        {
          "name": "Hat"
        }
      ]
    },
    {
      "name": "Ghost",
      "x": 120,
      "y": 80,
      "health": 5,
      "maxHealth": 30
    },
    {
      "name": "Ghost",
      "x": 240,
      "y": 160,
      "health": 1,
      "maxHealth": 30
    },
    {
      "name": "Void",
      "x": 225,
      "y": 45,
      "health": 20,
      "maxHealth": 20,
      "activated": false
    }
  ],
  "props": [
    {
      "name": "Cactus",
      "x": 50,
      "y": 30
    },
    {
      "name": "Cactus",
      "x": 120,
      "y": 190
    },
    {
      "name": "Skull",
      "x": 170,
      "y": 130
    },
    {
      "name": "Cross",
      "x": 352,
      "y": 150
    },
    {
      "name": "Tree",
      "x": 59,
      "y": 100
    },
    {
      "name": "Tree",
      "x": 210,
      "y": 60
    },
    {
      "name": "Tree",
      "x": 170,
      "y": 225
    }
  ],
  "items": [
    {
      "name": "Bottle",
      "x": 200,
      "y": 100
    },
    {
      "name": "Gun",
      "x": 100,
      "y": 190,
      "bulletVelocity": 10,
      "fireRate": 50,
      "damage": 2
    },
    {
      "name": "Wood",
      "x": 160,
      "y": 90
    },
    {
      "name": "Plank",
      "x": 220,
      "y": 180
    }
  ]
}